{
    "region_code": "23",
    "tags": [],
    "ip": 3525531838,
    "area_code": null,
    "latitude": 31.045600000000007,
    "hostnames": [],
    "postal_code": null,
    "dma_code": null,
    "country_code": "CN",
    "org": "Shanghai Institute Of Electric Power",
    "data": [
        {
            "hash": -2020837073,
            "ip": 3525531838,
            "org": "Shanghai Institute Of Electric Power",
            "isp": "China Education and Research Network Center",
            "transport": "tcp",
            "data": "HTTP/1.1 200 OK\r\nDate: Fri, 12 Oct 2018 18:24:12 GMT\r\nSet-Cookie: JSESSIONID=A9FE8F840DD80A3B6A7DB24505B48C85.tomcat102; Path=/eweb/; HttpOnly\r\nContent-Type: text/html;charset=UTF-8\r\nTransfer-Encoding: chunked\r\n\r\n",
            "asn": "AS4538",
            "port": 80,
            "hostnames": [],
            "location": {
                "city": null,
                "region_code": "23",
                "area_code": null,
                "longitude": 121.3997,
                "country_code3": "CHN",
                "latitude": 31.045600000000007,
                "postal_code": null,
                "dma_code": null,
                "country_code": "CN",
                "country_name": "China"
            },
            "timestamp": "2018-10-12T18:11:27.889346",
            "domains": [],
            "http": {
                "robots_hash": null,
                "redirects": [
                    {
                        "host": "210.35.88.190",
                        "data": "HTTP/1.1 302 Found\r\nDate: Fri, 12 Oct 2018 18:24:01 GMT\r\nSet-Cookie: JSESSIONID=E2104DC15C6C31D560FFD1AD20663506.tomcat102; Path=/; HttpOnly\r\nLocation: http://210.35.88.190/eweb/\r\nContent-Type: text/html;charset=UTF-8\r\nContent-Length: 0\r\n\r\n",
                        "location": "/"
                    },
                    {
                        "host": "210.35.88.190",
                        "data": "HTTP/1.1 302 Found\r\nDate: Fri, 12 Oct 2018 18:24:07 GMT\r\nSet-Cookie: JSESSIONID=1ADAA17A49C3A8848595248C68A23F4F.tomcat102; Path=/eweb/; HttpOnly\r\nLocation: http://210.35.88.190/eweb/login.jsp?reurl=%2F%2Findex.jsp%3Fnull\r\nContent-Type: text/html;charset=UTF-8\r\nContent-Length: 0\r\n\r\n",
                        "location": "/eweb/"
                    }
                ],
                "securitytxt": null,
                "title": "\u5c31\u4e1a\u4fe1\u606f\u7f51",
                "sitemap_hash": null,
                "robots": null,
                "favicon": null,
                "host": "210.35.88.190",
                "html": "\r\n\r\n\r\n\r\n\r\n\r\n\r\n\r\n\r\n\r\n\r\n\r\n\r\n\r\n\r\n<!DOCTYPE html PUBLIC \"-//W3C//DTD XHTML 1.0 Transitional//EN\" \"http://www.w3.org/TR/xhtml1/DTD/xhtml1-transitional.dtd\">\r\n<html xmlns=\"http://www.w3.org/1999/xhtml\">\r\n<head>\r\n<meta http-equiv=\"Content-Type\" content=\"text/html; charset=utf-8\" />\r\n<meta http-equiv=\"X-UA-Compatible\" content=\"IE=edge\"/>\r\n<link rel=\"stylesheet\" href=\"/eweb/jygl/index/css/index_style.css\" type=\"text/css\"/>\r\n<!-- Cascading Style Sheets -->\r\n\t\t<link rel=\"stylesheet\" href=\"/eweb/jygl/index/js/jquery-jDiaporama/page2.css\" type=\"text/css\"></link>\r\n\t\t<link href=\"/eweb/jygl/index/js/jquery-jDiaporama/style.css\" rel=\"stylesheet\" type=\"text/css\" />\r\n\t\t<!-- Javascript -->\r\n\t\t<script type=\"text/javascript\" src=\"/eweb/jygl/index/js/jquery-1.7.2.min.js\"></script>\r\n\t\t<script type=\"text/javascript\" src=\"/eweb/jygl/index/js/jquery-jDiaporama/js/jquery.jDiaporama.js\"></script>\r\n\t\t<script type=\"text/javascript\" src=\"/eweb/jygl/index/js/jquery-jDiaporama/js/script.js\"></script>\r\n\r\n<title>\u5c31\u4e1a\u4fe1\u606f\u7f51</title>\r\n<script language=\"JavaScript\" type=\"text/javascript\">\r\n\tfunction viewZpxx(id, modcode){\r\n\t\twindow.open('/eweb/jygl/zpfw.so?modcode='+modcode+'&subsyscode=zpfw&type=viewZpxx&id='+id);\r\n\t}\r\n</script>\r\n</head>\r\n<body>\r\n\t\r\n\r\n\r\n\r\n\r\n\r\n\r\n\r\n\r\n\r\n\r\n<script language=\"JavaScript\" type=\"text/javascript\">\r\n\tfunction testAuto(thisId, needLeng) {\r\n\t\tvar element = document.getElementById(thisId);\r\n\t\tvar nowLeng = element.innerText.length;\r\n\t\tif (nowLeng > needLeng) {\r\n\t\t\tvar nowWord = element.innerText.substr(0, needLeng) + '...';\r\n\t\t\telement.innerHTML = nowWord;\r\n\t\t}\r\n\t}\r\n\tfunction picDispatcher(url){\r\n\t\tif(url!=null&&url!=\"undefined\"&&url!=\"\"&&url!=\"null\"){\r\n\t\t\twindow.open(url);\r\n\t\t}\r\n\t}\r\n\t// \u9000\u51fa\u767b\u9646\r\n\tfunction loginout(){\r\n\t\twindow.location.href = \"/eweb/jygl/tpsjtu/logout.jsp\";\r\n\t}\r\n\t//\u641c\u7d22\r\n\tfunction queryInfo(){\r\n\t\tvar strTitle = document.getElementById(\"strTitle\").value;\r\n\t\tif(strTitle!=null && strTitle.length>0){\r\n\t\t\tvar url =\"/eweb/jygl/index.so?modcode=jyw_xwgg&subsyscode=jyw&type=searchNews&newsType=jyw&title=\" + strTitle;\r\n\t\t\twindow.open(url);\r\n\t\t}\r\n\t}\r\n\tfunction openLink(obj){\r\n    \tif(obj.value !='#'){\r\n    \t\twindow.open(obj.value);\r\n    \t}\r\n    }\r\n</script>\r\n<!--\u5934\u90e8-->\r\n<div class=\"ind_top\">\r\n   <ul class=\"ind_top_q\">\r\n   \t<li class=\"ind_top_l\">\r\n        \r\n        \t<a href=\"http://ycareer.shiep.edu.cn/eweb/jygl/jygl.so?type=searchZlgs\">\u4e13\u5229\u516c\u793a</a>\r\n      \t\r\n        \t<a href=\"http://ycareer.shiep.edu.cn/eweb/jygl/index.so?modcode=jyw_xwgg&subsyscode=jyw&type=searchNews&newsType=syxx\">\u751f\u6e90\u4fe1\u606f</a>\r\n      \t\r\n    </li>\r\n    <li class=\"ind_top_c\">\r\n      \t\r\n      \t\t<a href=\"/eweb/caslogin.jsp?jreurl=http://ycareer.shiep.edu.cn/eweb/jygl/index.so\">\u95e8\u6237\u767b\u5f55</a>\r\n      \t\r\n     \t\r\n         \t\t <a href=\"http://www.shiep.edu.cn\">\u5b66\u9662\u4e3b\u7f51\u7ad9</a>\r\n        \t \r\n      \t\t<input type=\"text\" class=\"search_input\" id=\"strTitle\" maxLength=\"30\" />\r\n      \t\t<input type=\"button\" class=\"search_btn\" onclick=\"queryInfo()\" />\r\n      </li>\r\n        </ul>\r\n    </div>\r\n    <!--\u5934\u90e8 END-->\r\n    <!--\u5bfc\u822a-->\r\n \t<div class=\"nav_wrap\">\r\n         <div class=\"nav\">\r\n             <ul class=\"nav_logo w1000_margin0\"><a href=\"/eweb/jygl/index.so\"><img class=\"logo\" src=\"/eweb/jygl/css/sjtuimgs/logo-index.png\" /></a></ul>\r\n             <div class=\"hr\"></div>\r\n             <ul class=\"nav_dh w1000_margin0\">\r\n                 <li class=\"dh_left\">\r\n                \r\n             <div class=\"dh_q\">\r\n              <a class=\"nav_tit\" target=\"_blank\" href=\"http://ycareer.shiep.edu.cn/eweb/jygl/index.so\">\r\n              \t\u9996\u9875\r\n              </a>\r\n             </div>\r\n           \r\n             <div class=\"dh_q\">\r\n              <a class=\"nav_tit\" target=\"_blank\" href=\"http://ycareer.shiep.edu.cn/eweb/jygl/index.so?modcode=jyw_xwgg&subsyscode=jyw&type=searchNews&newsType=jyw\">\r\n              \t\u65b0\u95fb\u516c\u544a\r\n              </a>\r\n             </div>\r\n           \r\n             <div class=\"dh_q\">\r\n              <a class=\"nav_tit\" target=\"_blank\" href=\"http://ycareer.shiep.edu.cn/eweb/jygl/zpfw.so?modcode=jygl_scfwzpxx&subsyscode=zpfw&type=searchZpxx&sysType=TPZPFW&zpxxType=new\">\r\n              \t\u62db\u8058\u70ed\u70b9\r\n              </a>\r\n             </div>\r\n           \r\n             <div class=\"dh_q\">\r\n              <a class=\"nav_tit\" target=\"_blank\" href=\"http://ycareer.shiep.edu.cn/eweb/jygl/index.so?type=gywm\">\r\n              \t\u5173\u4e8e\u6211\u4eec\r\n              </a>\r\n             </div>\r\n           \r\n                 </li>\r\n                 <li class=\"dh_right\">\r\n           \t<span class=\"dh_time\" id=\"myDate\"></span>\r\n               <span class=\"dh_week\" id=\"myWeek\"></span>\r\n               <script type=\"text/javascript\">\r\n           \t\tvar myDate=new Date();\r\n           \t\tdocument.getElementById(\"myDate\").innerHTML=myDate.getFullYear()+\"\u5e74\"+(myDate.getMonth()+1)+\"\u6708\"+myDate.getDate()+\"\u65e5\";\r\n           \t\tvar day =myDate.getDay();\r\n           \t\tvar week =\"\";\r\n           \t\tif(day==0){\r\n           \t\t\tweek =\"\u661f\u671f\u65e5\";\r\n           \t\t}\r\n           \t\tif(day==1){\r\n           \t\t\tweek =\"\u661f\u671f\u4e00\";\r\n           \t\t}\r\n           \t\tif(day==2){\r\n           \t\t\tweek =\"\u661f\u671f\u4e8c\";\r\n           \t\t}\r\n           \t\tif(day==3){\r\n           \t\t\tweek =\"\u661f\u671f\u4e09\";\r\n           \t\t}\r\n           \t\tif(day==4){\r\n           \t\t\tweek =\"\u661f\u671f\u56db\";\r\n           \t\t}\r\n           \t\tif(day==5){\r\n           \t\t\tweek =\"\u661f\u671f\u4e94\";\r\n           \t\t}\r\n           \t\tif(day==6){\r\n           \t\t\tweek =\"\u661f\u671f\u516d\";\r\n           \t\t}\r\n           \t\tdocument.getElementById(\"myWeek\").innerHTML=week;\r\n           \t</script> \r\n    <select class=\"iselect\" onchange=\"openLink(this)\">\r\n\t\t<option value=\"#\">\u70ed\u70b9\u4e13\u9898</option>\r\n\t  \t\r\n             <option value=\"http://news.shiep.edu.cn/\">\u6821\u56ed\u5feb\u8baf  </option>\r\n       \r\n    </select> \r\n\t<select class=\"iselect\" onchange=\"openLink(this)\">\r\n\t\t<option value=\"#\">\u5feb\u901f\u901a\u9053</option>\r\n\t\t\r\n        \t\t<option value=\"http://www.shiep.edu.cn/\">\u5b66\u6821\u7f51\u7ad9   </option>\r\n       \t  \r\n\t</select>\r\n</li>\r\n              </ul>\r\n          </div>\r\n      </div>\r\n  <!--\u5bfc\u822a END-->\r\n\t\r\n    <!--\u8f6e\u64ad\u56fe-->\r\n    <div class=\"w1000_margin0\" style=\"height:353px;\">\r\n\t\t<ul class=\"diaporama1\" style=\"width:1000px\">\r\n\t\t\r\n\t\t\t\t<li >\t\t\r\n\t\t\t\t\t<img id=\"cursorH\" width=\"1000\" height=\"352\" src=\"/eweb/images/newspic/MgxEV8CiePHFZnLqbex8uU.jpg\" onclick=\"picDispatcher('http://ycareer.shiep.edu.cn/eweb/jygl/index.so?modcode=jyw_xwgg&subsyscode=jyw&type=view&newsType=jyw&id=45565d2f04b14b5d8ffb03251176f1a9')\" style=\"cursor:pointer;\"  />\t\r\n\t\t\t\t</li>\r\n\t\t\r\n\t\t\t\t<li>\r\n\t\t\t\t\t<img width=\"1000\" height=\"352\" src=\"/eweb/images/newspic/4P5FZZA4A4tVaXPnup1vqe.jpg\" />\r\n\t\t\t\t</li>\t\t\r\n\t\t\r\n\t\t\t\t<li>\r\n\t\t\t\t\t<img width=\"1000\" height=\"352\" src=\"/eweb/images/newspic/LqfwgFZYmy1oZFybgXM6ho.jpg\" />\r\n\t\t\t\t</li>\t\t\r\n\t\t\r\n\t\t\t\t<li>\r\n\t\t\t\t\t<img width=\"1000\" height=\"352\" src=\"/eweb/images/newspic/HkfwyWWJ7YnAbcW4R2kKtq.jpg\" />\r\n\t\t\t\t</li>\t\t\r\n\t\t\r\n\t\t\t\t<li>\r\n\t\t\t\t\t<img width=\"1000\" height=\"352\" src=\"/eweb/images/newspic/TcbY26Vag3EdQ2EwqpsxGF.jpg\" />\r\n\t\t\t\t</li>\t\t\r\n\t\t\r\n\t\t\t\t<li>\r\n\t\t\t\t\t<img width=\"1000\" height=\"352\" src=\"/eweb/images/newspic/AByxuggdDyLpafzqdxoxj4.jpg\" />\r\n\t\t\t\t</li>\t\t\r\n\t\t\r\n\t\t </ul>\r\n      </div>\r\n       <!--\u8f6e\u64ad\u56fe end-->\r\n       <!--\u56db\u7c7b\u5bfc\u822a-->\r\n       \r\n        <div class=\"wl_q\">\r\n        \t<ul>\r\n            \t<li>\r\n                \t<a style=\"position:relative;\" href=\"javascript:void(0);\" ><img src=\"/eweb/jygl/index/images/index_05_30.png\" /></a>\r\n\t\t\t\t\t\r\n\t\t\t\t\t\t<!-- \u6ca1\u6709\u7edf\u4e00\u8eab\u4efd\u8ba4\u8bc1\u7684\u5b66\u6821\u8d70\u6b64\u767b\u5f55\r\n\t\t\t\t\t\t<a class=\"zxs_dl\" href=\"/eweb/jygl/index/login.jsp\">\u767b\u5f55</a>\r\n\t\t\t\t\t\t-->\r\n\t\t\t\t\t\t<a class=\"zxs_dl\" href=\"/eweb/caslogin.jsp?jreurl=http://ycareer.shiep.edu.cn/eweb/jygl/index.so\">\u767b\u5f55</a>\r\n\t\t\t\t\t\r\n                \t<div class=\"wl_hover1\">\r\n                    \r\n\t\t                 \t     <ul>\r\n\t\t                         <p>\r\n\t\t                      \t    <a id=\"RzYx33NtpSWXgtPLCjAuQH\" href=\"http://ycareer.shiep.edu.cn/eweb/jygl/jygl.so\" target=\"_blank\">\u5c31\u4e1a\u7ba1\u7406</a>\r\n\t\t                          </p>\r\n\t\t                         \r\n\t\t                   \r\n\t\t                      \t   <li><a id=\"EFTs4Y17k85Q6ANtz4yzEQ\" href=\"http://ycareer.shiep.edu.cn/eweb/jygl/jygl.so?\" target=\"_blank\">\u4e2a\u4eba\u4fe1\u606f\u6838\u5bf9</a></li>\t\r\n\t\t                         \r\n\t\t                   \r\n\t\t                      \t   <li><a id=\"LLHLKeG7NVG55PKREu5HiH\" href=\"http://ycareer.shiep.edu.cn/eweb/jygl/jygl.so?\" target=\"_blank\">\u63a8\u8350\u8868\u81ea\u5236</a></li>\t\r\n\t\t                         \r\n\t\t                   \r\n\t\t                      \t   <li><a id=\"FnbwLwf1zCJERREXHjBV3a\" href=\"http://ycareer.shiep.edu.cn/eweb/jygl/jygl.so?type=forward&entityId=XS_JYGL_XSYXBYS&subsyscode=jygl&modcode=jygl_xsyxbysdj\" target=\"_blank\">\u7533\u8bf7\u4f18\u79c0\u6bd5\u4e1a\u751f</a></li>\t\r\n\t\t                         \r\n\t\t                   \r\n\t\t                      \t   <li><a id=\"HXmxJhit4hvqB6quVKrLva\" href=\"http://ycareer.shiep.edu.cn/eweb/jygl/jygl.so?\" target=\"_blank\">\u6bd5\u4e1a\u53bb\u5411\u767b\u8bb0</a></li>\t\r\n\t\t                         \r\n\t\t                    \r\n                           \t     </ul>\r\n                           \t     \r\n\t\t                 \t     <ul>\r\n\t\t                         <p>\r\n\t\t                      \t    <a id=\"C6Qe5szrSDrLSNW3qBtKJv\" href=\"http://ycareer.shiep.edu.cn/eweb/jygl/zpfw.so\" target=\"_blank\">\u62db\u8058\u670d\u52a1</a>\r\n\t\t                          </p>\r\n\t\t                         \r\n\t\t                   \r\n\t\t                      \t   <li><a id=\"4iMKaMkSgxxAR9LRqRRars\" href=\"http://ycareer.shiep.edu.cn/eweb/jygl/zpfw.so?type=zpxx\" target=\"_blank\">\u62db\u8058\u4fe1\u606f</a></li>\t\r\n\t\t                         \r\n\t\t                   \r\n\t\t                      \t   <li><a id=\"5ih9YSJ3ymKBiiezKtrn3A\" href=\"http://ycareer.shiep.edu.cn/eweb/jygl/zpfw.so?type=xjh\" target=\"_blank\">\u5ba3\u8bb2\u4f1a\u4fe1\u606f</a></li>\t\r\n\t\t                         \r\n\t\t                   \r\n\t\t                      \t   <li><a id=\"RwtgnWSQimLne1KhvEB9KU\" href=\"http://ycareer.shiep.edu.cn/eweb/jygl/zpfw.so?type=dwfw\" target=\"_blank\">\u62db\u8058\u6307\u5357</a></li>\t\r\n\t\t                         \r\n\t\t                   \r\n                      \t          </ul>\r\n                      \t\r\n                        <div class=\"clear\"></div>\r\n                    </div>\r\n                </li>\r\n                <li>\r\n                \t<a style=\"position:relative;\" href=\"javascript:void(0);\" ><img src=\"/eweb/jygl/index/images/index_09_30.png\" /></a>\r\n                \t<div class=\"yrdw_dl_dl\">\r\n                \t\r\n                \t      <a class=\"sk_a\" href=\"/eweb/jygl/zpfw.so\">\u767b\u5f55</a>\r\n                \t      <a class=\"sk_a\" href=\"/eweb/jygl/jyglext.so?type=dwzc\">\u6ce8\u518c</a>\r\n                \t\r\n                \t</div>\r\n                    <div class=\"wl_hover3\">\r\n                      \r\n\t\t                 \t     <ul>\r\n\t\t                         <p>\r\n\t\t                      \t    <a id=\"WktpnrnGa5QB9WXjk9VoUw\" href=\"http://ycareer.shiep.edu.cn/eweb/jygl/zpfw.so\" target=\"_blank\">\u62db\u8058\u670d\u52a1</a>\r\n\t\t                          </p>\r\n\t\t                         \r\n\t\t                         \r\n\t\t                      \t   <li><a id=\"S6yFcZSDrDExN1dvrkhSnY\" href=\"http://ycareer.shiep.edu.cn/eweb/jygl/zpfw.so?  type=forward&entityId=DWFW_JYGL_DWXX&subsyscode=zpfw&modcode=jygl_dwfwdwxx\" target=\"_blank\">\u5355\u4f4d\u4fe1\u606f\u7ef4\u62a4</a></li>\t\r\n\t\t                         \r\n\t\t                         \r\n\t\t                      \t   <li><a id=\"2pcvDfu87nugFVm8626pZ8\" href=\"http://ycareer.shiep.edu.cn/eweb/jygl/zpfw.so?\" target=\"_blank\">\u62db\u8058\u4f1a\u62a5\u540d</a></li>\t\r\n\t\t                         \r\n\t\t                         \r\n\t\t                      \t   <li><a id=\"Vo9wJwKGpbCmpn5AgW6KCa\" href=\"http://ycareer.shiep.edu.cn/eweb/jygl/zpfw.so?\" target=\"_blank\">\u53d1\u5e03\u62db\u8058\u4fe1\u606f</a></li>\t\r\n\t\t                         \r\n\t\t                         \r\n\t\t                      \t   <li><a id=\"R8pwvxrrbzPBG6j79ZGHLT\" href=\"http://ycareer.shiep.edu.cn/eweb/jygl/zpfw.so?\" target=\"_blank\">\u5ba3\u8bb2\u4f1a\u62a5\u540d</a></li>\t\r\n\t\t                         \r\n\t\t                          \r\n                           \t     </ul>\r\n                           \t     \r\n\t\t                 \t     <ul>\r\n\t\t                         <p>\r\n\t\t                      \t    <a id=\"5fxeqVbMiUFWqcajzhdfGh\" href=\"http://ycareer.shiep.edu.cn/index.htm\" target=\"_blank\">\u5176\u4ed6\u516c\u5171\u4fe1\u606f</a>\r\n\t\t                          </p>\r\n\t\t                         \r\n\t\t                         \r\n\t\t                      \t   <li><a id=\"Ta5kiCNwaDmaaTmPoeVawi\" href=\"/shdl/jygl/index.so?type=yxjs\" target=\"_blank\">\u9662\u7cfb\u4e13\u4e1a</a></li>\t\r\n\t\t                         \r\n\t\t                         \r\n\t\t                      \t   <li><a id=\"Qui1gLqK14jsHEN4xMKn9C\" href=\"news/list.htm?nType=1\" target=\"_blank\">\u751f\u6e90\u4fe1\u606f</a></li>\t\r\n\t\t                         \r\n\t\t                         \r\n                      \t          </ul>\r\n                      \t\r\n                        <div class=\"clear\"></div>\r\n                    </div>\t\r\n                </li>\r\n                <li>\r\n                \t<a style=\"position:relative;\" href=\"javascript:void(0);\" ><img src=\"/eweb/jygl/index/images/index_11_30.png\" /></a>\r\n                \t\r\n\t\t\t\t\t<a class=\"xy_dl\" href=\"/eweb/caslogin.jsp?jreurl=http://ycareer.shiep.edu.cn/eweb/jygl/index.so\">\u767b\u5f55</a>\r\n\t\t\t\t\t\r\n                \t<div class=\"wl_hover4\">\r\n                      \r\n\t\t                 \t     <ul>\r\n\t\t                         <p>\r\n\t\t                      \t    <a id=\"TuFLTvksDCZbvu3yKpna6F\" href=\"http://ycareer.shiep.edu.cn/eweb/jygl/zpfw.so\" target=\"_blank\">\u62db\u8058\u670d\u52a1</a>\r\n\t\t                          </p>\r\n\t\t                         \r\n\t\t                         \r\n\t\t                      \t   <li><a id=\"EfRSUYipKQvWmN9YEyYu69\" href=\"http://ycareer.shiep.edu.cn/eweb/jygl/zpfw.so?type=zpxx\" target=\"_blank\">\u62db\u8058\u4fe1\u606f</a></li>\t\r\n\t\t                         \r\n\t\t                         \r\n\t\t                      \t   <li><a id=\"8LTo7Gz1g56uPNcka4Xqe5\" href=\"http://ycareer.shiep.edu.cn/eweb/jygl/zpfw.so?type=xjh\" target=\"_blank\">\u5ba3\u8bb2\u4f1a\u4fe1\u606f</a></li>\t\r\n\t\t                         \r\n\t\t                         \r\n                      \t          </ul>\r\n                      \t\r\n                        <div class=\"clear\"></div>\r\n                    </div>\r\n                </li>\r\n                <li>\r\n                \t<a style=\"position:relative;\" href=\"javascript:void(0);\" ><img src=\"/eweb/jygl/index/images/index_07_30.png\" /></a>\r\n\t\t\t\t\t\r\n\t\t\t\t\t\t<a class=\"js_dl\" href=\"/eweb/caslogin.jsp?jreurl=http://ycareer.shiep.edu.cn/eweb/jygl/index.so\">\u767b\u5f55</a>\r\n\t\t\t\t\t\r\n                \t<div class=\"wl_hover2\">\r\n                       \r\n\t\t                 \t     <ul>\r\n\t\t                         <p>\r\n\t\t                      \t    <a id=\"NS7vyxqYzjbMhZfxv8UKMw\" href=\"http://ycareer.shiep.edu.cn/eweb/jygl/jygl.so\" target=\"_blank\">\u5c31\u4e1a\u7ba1\u7406</a>\r\n\t\t                          </p>\r\n\t\t                         \r\n\t\t                         \r\n\t\t                      \t   <li><a id=\"97dmpetN27yoGWqJgVxpnT\" href=\"http://ycareer.shiep.edu.cn/eweb/jygl/jygl.so?type=forward&entityId=XJYGL_JYGL_XSXXKW&subsyscode=jygl&modcode=jygl_xjyglxsxxkw\" target=\"_blank\">\u5b66\u751f\u4fe1\u606f\u52d8\u8bef</a></li>\t\r\n\t\t                         \r\n\t\t                         \r\n\t\t                      \t   <li><a id=\"AdKLBFjdJU8x69kWwALERY\" href=\"http://ycareer.shiep.edu.cn/eweb/jygl/jygl.so?type=forward&entityId=XJYGL_JYGL_XSTJBXX&subsyscode=jygl&modcode=jygl_xjygltjbgl\" target=\"_blank\">\u63a8\u8350\u8868\u5ba1\u6838</a></li>\t\r\n\t\t                         \r\n\t\t                         \r\n\t\t                      \t   <li><a id=\"WszhPJC4bTggCw4TMTwCdS\" href=\"http://ycareer.shiep.edu.cn/eweb/jygl/jygl.so?type=forward&entityId=XJYGL_JYGL_BYQX&subsyscode=jygl&modcode=jygl_xjyglbyqxgl\" target=\"_blank\">\u6bd5\u4e1a\u53bb\u5411\u7ba1\u7406</a></li>\t\r\n\t\t                         \r\n\t\t                         \r\n\t\t                      \t   <li><a id=\"KEA9kfQnnBQrmQsr2WR9CR\" href=\"http://ycareer.shiep.edu.cn/eweb/jygl/jygl.so?type=forward&entityId=XJYGL_JYGL_XSYXBYS&subsyscode=jygl&modcode=jygl_xjyglyxbysdj\" target=\"_blank\">\u4f18\u79c0\u6bd5\u4e1a\u751f\u5ba1\u6838</a></li>\t\r\n\t\t                         \r\n\t\t                         \r\n\t\t                      \t   <li><a id=\"VSjK9XH5DRDRfSFZengau6\" href=\"http://ycareer.shiep.edu.cn/eweb/jygl/jygl.so?type=forward&entityId=YX_JYGL_XSXXKW&subsyscode=jygl&modcode=jygl_yxxsxxkw\" target=\"_blank\">\u9662\u7cfb\u5b66\u751f\u4fe1\u606f\u52d8\u8bef</a></li>\t\r\n\t\t                         \r\n\t\t                         \r\n\t\t                      \t   <li><a id=\"zZKLcFP4RpSG3Y8fUQL8n\" href=\"http://ycareer.shiep.edu.cn/eweb/jygl/jygl.so?type=forward&entityId=YX_JYGL_XSTJBXX&subsyscode=jygl&modcode=jygl_yxtjbgl\" target=\"_blank\">\u9662\u7cfb\u63a8\u8350\u8868\u5ba1\u6838</a></li>\t\r\n\t\t                         \r\n\t\t                         \r\n\t\t                      \t   <li><a id=\"5bbCg8ztQNPwKZ5pjo2hKV\" href=\"http://ycareer.shiep.edu.cn/eweb/jygl/jygl.so?type=forward&entityId=YX_JYGL_BYQX&subsyscode=jygl&modcode=jygl_yxbyqxgl\" target=\"_blank\">\u9662\u7cfb\u6bd5\u4e1a\u53bb\u5411\u7ba1\u7406</a></li>\t\r\n\t\t                         \r\n\t\t                         \r\n\t\t                      \t   <li><a id=\"29D6epwVQfV85RGBQ2gZcY\" href=\"http://ycareer.shiep.edu.cn/eweb/jygl/jygl.so?type=forward&entityId=YX_JYGL_XSYXBYS&subsyscode=jygl&modcode=jygl_yxbysdj\" target=\"_blank\">\u9662\u7cfb\u4f18\u79c0\u6bd5\u4e1a\u751f</a></li>\t\r\n\t\t                         \r\n\t\t                          \r\n                           \t     </ul>\r\n                           \t     \r\n\t\t                 \t     <ul>\r\n\t\t                         <p>\r\n\t\t                      \t    <a id=\"GGg4khuTLWscSiFv2FFWsi\" href=\"http://ycareer.shiep.edu.cn/eweb/jygl/zpfw.so\" target=\"_blank\">\u62db\u8058\u670d\u52a1</a>\r\n\t\t                          </p>\r\n\t\t                         \r\n\t\t                         \r\n\t\t                      \t   <li><a id=\"VFEMSgMAVGzSxkMAico9R6\" href=\"http://ycareer.shiep.edu.cn/eweb/jygl/zpfw.so?type=forward&entityId=SCFW_JYGL_DWXX&subsyscode=zpfw&modcode=jygl_scfwyrdw\" target=\"_blank\">\u5355\u4f4d\u4fe1\u606f\u5ba1\u6838</a></li>\t\r\n\t\t                         \r\n\t\t                         \r\n\t\t                      \t   <li><a id=\"3xpXVAez3N8ojVbWXhvVwz\" href=\"http://ycareer.shiep.edu.cn/eweb/jygl/zpfw.so?type=forward&entityId=SCFW_JYGL_ZPXX&subsyscode=zpfw&modcode=jygl_scfwzpxx\" target=\"_blank\">\u62db\u8058\u4fe1\u606f\u53d1\u5e03</a></li>\t\r\n\t\t                         \r\n\t\t                         \r\n\t\t                      \t   <li><a id=\"DMQB4U8jXGjVCrNRxfvgMW\" href=\"http://ycareer.shiep.edu.cn/eweb/jygl/zpfw.so?type=forward&entityId=SCFW_JYGL_XJHBMXX&subsyscode=zpfw&modcode=jygl_scfwxjhgl\" target=\"_blank\">\u4e13\u573a\u5ba3\u8bb2\u4f1a\u7ba1\u7406</a></li>\t\r\n\t\t                         \r\n\t\t                          \r\n                           \t     </ul>\r\n                           \t     \r\n\t\t                 \t     <ul>\r\n\t\t                         <p>\r\n\t\t                      \t    <a id=\"NPFwk6S2D7f6ihSQtu1W2L\" href=\"http://ycareer.shiep.edu.cn/eweb/jygl/jyw.so\" target=\"_blank\">\u5c31\u4e1a\u7f51</a>\r\n\t\t                          </p>\r\n\t\t                         \r\n\t\t                         \r\n                      \t          </ul>\r\n                      \t\t\r\n\t                    <div class=\"clear\"></div>\r\n                    </div>\r\n                </li>\r\n            </ul>\r\n        </div>\r\n        <!--\u56db\u7c7b\u5bfc\u822a END-->\r\n        <!--\u516c\u544a-->\r\n        <div class=\"gg_q\">\r\n        \t<div class=\"w1000_margin0\">\r\n                <div class=\"gg_left\">\r\n                    <div class=\"gg_left_top\">\r\n                        <ul class=\"gg_l\">\r\n\t\t\t            \t<h2 class=\"gg_l_tit\">\r\n\t\t\t            \t\t<a target=\"_blank\" href=\"/eweb/jygl/index.so?modcode=jyw_xwgg&subsyscode=jyw&type=searchNews&newsType=jyw\">\u516c\u544a\u65b0\u95fb</a><a target=\"_blank\" class=\"gg_more\" href=\"/eweb/jygl/index.so?modcode=jyw_xwgg&subsyscode=jyw&type=searchNews&newsType=jyw\">\u66f4\u591a</a>\r\n\t\t\t            \t</h2>\r\n\t\t\t                \r\n\t\t\t\t\t\t\t   \r\n\t\t\t                 <li title=\"\u6caa\u9ad8\u6821\u516c\u5e03\"\u5c31\u4e1a\u8d28\u91cf\u62a5\u544a\" \u6bd5\u4e1a\u6c42\u804c\u5e73\u5747\u97003\u4e2a\u6708 \">\r\n\t\t\t                 \t<a target=\"_blank\" href=\"/eweb/jygl/index.so?modcode=jyw_xwgg&subsyscode=jyw&type=view&newsType=jyw&id=b2576f4a46fe4e139c73d106468fd123\">\r\n\t\t\t                 \t \u6caa\u9ad8\u6821\u516c\u5e03\"\u5c31\u4e1a\u8d28\u91cf\u62a5\u544a\" \u6bd5\u4e1a\u6c42\u804c\u5e73\u5747\u97003\u4e2a\u6708 \r\n\t\t\t                 \t</a>\r\n\t\t\t                 </li>\r\n\t\t\t                 \r\n\t\t\t\t\t\t\t   \r\n\t\t\t                 <li title=\"\u4e2d\u5357\u8d22\u7ecf\u653f\u6cd5\u5927\u5b66\u7edf\u8ba1\u663e\u793a\uff1a\u5973\u751f\u5c31\u4e1a\u7387\u9ad8\u4e8e\u7537\u751f\">\r\n\t\t\t                 \t<a target=\"_blank\" href=\"/eweb/jygl/index.so?modcode=jyw_xwgg&subsyscode=jyw&type=view&newsType=jyw&id=45565d2f04b14b5d8ffb03251176f1a9\">\r\n\t\t\t                 \t \u4e2d\u5357\u8d22\u7ecf\u653f\u6cd5\u5927\u5b66\u7edf\u8ba1\u663e\u793a\uff1a\u5973\u751f\u5c31\u4e1a\u7387\u9ad8\u4e8e\u7537\u751f\r\n\t\t\t                 \t</a>\r\n\t\t\t                 </li>\r\n\t\t\t                 \r\n\t\t\t\t\t\t\t   \r\n\t\t\t                 <li title=\"\u798f\u5efa\uff1a\u5b9e\u884c\u5c31\u4e1a\u62a5\u544a\u5236 \u4e25\u7981\u5c31\u4e1a\u7387\u9020\u5047\">\r\n\t\t\t                 \t<a target=\"_blank\" href=\"/eweb/jygl/index.so?modcode=jyw_xwgg&subsyscode=jyw&type=view&newsType=jyw&id=63280b0bad3d4f31b0630660b914ce0d\">\r\n\t\t\t                 \t \u798f\u5efa\uff1a\u5b9e\u884c\u5c31\u4e1a\u62a5\u544a\u5236 \u4e25\u7981\u5c31\u4e1a\u7387\u9020\u5047\r\n\t\t\t                 \t</a>\r\n\t\t\t                 </li>\r\n\t\t\t                 \r\n\t\t\t\t\t\t\t   \r\n\t\t\t                 <li title=\"\u7f16\u5236\u5c31\u4e1a\u8d28\u91cf\u62a5\u544a\uff0c\u9ad8\u804c\u5e94\u5438\u53d6\u90e8\u5c5e\u9ad8\u6821\u6559\u8bad\">\r\n\t\t\t                 \t<a target=\"_blank\" href=\"/eweb/jygl/index.so?modcode=jyw_xwgg&subsyscode=jyw&type=view&newsType=jyw&id=64389621de7a420db4771bbc9194ac20\">\r\n\t\t\t                 \t \u7f16\u5236\u5c31\u4e1a\u8d28\u91cf\u62a5\u544a\uff0c\u9ad8\u804c\u5e94\u5438\u53d6\u90e8\u5c5e\u9ad8\u6821\u6559\u8bad\r\n\t\t\t                 \t</a>\r\n\t\t\t                 </li>\r\n\t\t\t                 \r\n\t\t\t\t\t\t\t   \r\n\t\t\t                 <li title=\"\u6559\u80b2\u90e8\u9996\u6b21\u7ec4\u7ec775\u6240\u9ad8\u6821\u53d1\u5e03\u5c31\u4e1a\u62a5\u544a \u4ec5\u4e09\u6210\u53ca\u683c\">\r\n\t\t\t                 \t<a target=\"_blank\" href=\"/eweb/jygl/index.so?modcode=jyw_xwgg&subsyscode=jyw&type=view&newsType=jyw&id=85239e737f0941139f9b6a1b4afd13bc\">\r\n\t\t\t                 \t \u6559\u80b2\u90e8\u9996\u6b21\u7ec4\u7ec775\u6240\u9ad8\u6821\u53d1\u5e03\u5c31\u4e1a\u62a5\u544a \u4ec5\u4e09\u6210\u53ca\u683c\r\n\t\t\t                 \t</a>\r\n\t\t\t                 </li>\r\n\t\t\t                 \r\n\t\t\t\t\t\t\t   \r\n\t\t\t                 <li title=\"\u9ad8\u6821\u6bd5\u4e1a\u751f\u5c31\u4e1a\u8d28\u91cf\u62a5\u544a\uff1a\u8d28\u91cf\u6709\u5f85\u63d0\u9ad8\">\r\n\t\t\t                 \t<a target=\"_blank\" href=\"/eweb/jygl/index.so?modcode=jyw_xwgg&subsyscode=jyw&type=view&newsType=jyw&id=44cec0f91d204178b643ace182baf35d\">\r\n\t\t\t                 \t \u9ad8\u6821\u6bd5\u4e1a\u751f\u5c31\u4e1a\u8d28\u91cf\u62a5\u544a\uff1a\u8d28\u91cf\u6709\u5f85\u63d0\u9ad8\r\n\t\t\t                 \t</a>\r\n\t\t\t                 </li>\r\n\t\t\t                 \r\n\t\t\t\t\t\t\t   \r\n\t\t\t                 <li title=\"\u9ad8\u6821\u5c31\u4e1a\u8d28\u91cf\u62a5\u544a \u6c34\u5206\u5e94\u8be5\u201c\u6324\u4e00\u6324\u201d\">\r\n\t\t\t                 \t<a target=\"_blank\" href=\"/eweb/jygl/index.so?modcode=jyw_xwgg&subsyscode=jyw&type=view&newsType=jyw&id=2b2550662c4147378369422ef616efdb\">\r\n\t\t\t                 \t \u9ad8\u6821\u5c31\u4e1a\u8d28\u91cf\u62a5\u544a \u6c34\u5206\u5e94\u8be5\u201c\u6324\u4e00\u6324\u201d\r\n\t\t\t                 \t</a>\r\n\t\t\t                 </li>\r\n\t\t\t                 \r\n\t\t\t\t\t\t\t   \r\n\t\t\t                 <li title=\"\u6559\u80b2\u90e8\u53d1\u5e03\u4e2d\u56fd\u7279\u8272\u65b0\u578b\u9ad8\u6821\u667a\u5e93\u5efa\u8bbe\u63a8\u8fdb\u8ba1\u5212\">\r\n\t\t\t                 \t<a target=\"_blank\" href=\"/eweb/jygl/index.so?modcode=jyw_xwgg&subsyscode=jyw&type=view&newsType=jyw&id=f0cae2c216c94f02957133c988c62b0b\">\r\n\t\t\t                 \t \u6559\u80b2\u90e8\u53d1\u5e03\u4e2d\u56fd\u7279\u8272\u65b0\u578b\u9ad8\u6821\u667a\u5e93\u5efa\u8bbe\u63a8\u8fdb\u8ba1\u5212\r\n\t\t\t                 \t</a>\r\n\t\t\t                 </li>\r\n\t\t\t                 \r\n\t\t\t\t\t\t\t   \r\n\t\t\t                 <li title=\"\u9996\u62792013\u5e74\u9ad8\u6821\u5c31\u4e1a\u8d28\u91cf\u62a5\u544a\u51fa\u7089 20\u9ad8\u6821\u6652\u5c31\u4e1a\">\r\n\t\t\t                 \t<a target=\"_blank\" href=\"/eweb/jygl/index.so?modcode=jyw_xwgg&subsyscode=jyw&type=view&newsType=jyw&id=673be57108a4425196aa28b53bb89496\">\r\n\t\t\t                 \t \u9996\u62792013\u5e74\u9ad8\u6821\u5c31\u4e1a\u8d28\u91cf\u62a5\u544a\u51fa\u7089 20\u9ad8\u6821\u6652\u5c31\u4e1a\r\n\t\t\t                 \t</a>\r\n\t\t\t                 </li>\r\n\t\t\t                 \r\n\t\t\t             </ul>\r\n                        <ul class=\"gg_c\">\r\n                            <h2 class=\"gg_l_tit\">\r\n\t\t\t            \t\t<a target=\"_blank\" href=\"/eweb/jygl/zpfw.so?modcode=jygl_scfwzpxx&subsyscode=zpfw&type=searchZprd&sysType=TPZPFW&zpxxType=new\">\u62db\u8058\u70ed\u70b9</a><a target=\"_blank\" class=\"gg_more\" href=\"/eweb/jygl/zpfw.so?modcode=jygl_scfwzpxx&subsyscode=zpfw&type=searchZprd&sysType=TPZPFW&zpxxType=new\">\u66f4\u591a</a>\r\n\t\t\t            \t</h2>\r\n                               \r\n\t\t\t\t\t   \t       \t\t<li>\r\n\t\t\t\t\t\t\t\t   \t\t<div style=\"float:left;text-align: left;width:500px; \">\r\n\t\t\t\t\t\t\t\t   \t       <a target=\"_blank\" href=\"/eweb/jygl/zpfw.so?modcode=jygl_zpfwzpgg&subsyscode=zpfw&type=view&id=QQpjKgv2jYaUPWgHEyCbMr\">\r\n\t\t\t\t\t\t\t\t   \t\t   \t \u4e2d\u56fd\u5927\u5510\u96c6\u56e2\u79d1\u5b66\u6280\u672f\u7814\u7a76\u9662\u6709\u9650\u516c\u53f82019\u5e74\u6bd5\u4e1a\u751f\u62db\u8058\u516c\u544a\r\n\t\t\t\t\t\t\t\t   \t       </a>\r\n\t\t\t\t\t\t\t\t   \t    </div>\r\n\t\t\t\t\t\t\t\t  </li>\r\n\t\t\t\t\t\t\t\t\r\n\t\t\t\t\t   \t       \t\t<li>\r\n\t\t\t\t\t\t\t\t   \t\t<div style=\"float:left;text-align: left;width:500px; \">\r\n\t\t\t\t\t\t\t\t   \t       <a target=\"_blank\" href=\"/eweb/jygl/zpfw.so?modcode=jygl_zpfwzpgg&subsyscode=zpfw&type=view&id=UrwEXu3WVqScuB1YxYW4rh\">\r\n\t\t\t\t\t\t\t\t   \t\t   \t \u6b66\u6c49\u4e1c\u6e56\u65b0\u6280\u672f\u5f00\u53d1\u533a2018\u5e74\u201c\u624d\u805a\u5149\u8c37\u201d\u4e0a\u6d77\u7ad9\u62db\u8058\u4f1a\u5c97\u4f4d\u4fe1\u606f\r\n\t\t\t\t\t\t\t\t   \t       </a>\r\n\t\t\t\t\t\t\t\t   \t    </div>\r\n\t\t\t\t\t\t\t\t  </li>\r\n\t\t\t\t\t\t\t\t\r\n\t\t\t\t\t   \t       \t\t<li>\r\n\t\t\t\t\t\t\t\t   \t\t<div style=\"float:left;text-align: left;width:500px; \">\r\n\t\t\t\t\t\t\t\t   \t       <a target=\"_blank\" href=\"/eweb/jygl/zpfw.so?modcode=jygl_zpfwzpgg&subsyscode=zpfw&type=view&id=BX8WLGgygsL5wWTDr6qGak\">\r\n\t\t\t\t\t\t\t\t   \t\t   \t \u4e2d\u56fd\u56fd\u9645\u8fdb\u53e3\u535a\u89c8\u4f1a\u548c\u56fd\u5bb6\u4f1a\u5c55\u4e2d\u5fc3\u5b9e\u4e60\u62db\u8058\r\n\t\t\t\t\t\t\t\t   \t       </a>\r\n\t\t\t\t\t\t\t\t   \t    </div>\r\n\t\t\t\t\t\t\t\t  </li>\r\n\t\t\t\t\t\t\t\t\r\n\t\t\t\t\t   \t       \t\t<li>\r\n\t\t\t\t\t\t\t\t   \t\t<div style=\"float:left;text-align: left;width:500px; \">\r\n\t\t\t\t\t\t\t\t   \t       <a target=\"_blank\" href=\"/eweb/jygl/zpfw.so?modcode=jygl_zpfwzpgg&subsyscode=zpfw&type=view&id=QDdxvqsLa6cvPJ37HuXNBy\">\r\n\t\t\t\t\t\t\t\t   \t\t   \t \u957f\u4e09\u89d2\u5730\u533a\u4eba\u624d\u4ea4\u6d41\u6d3d\u8c08\u4f1a\u66a82018\u5c4a\u9ad8\u6821\u6bd5\u4e1a\u751f\u62e9\u4e1a\u62db\u8058\u4f1a\r\n\t\t\t\t\t\t\t\t   \t       </a>\r\n\t\t\t\t\t\t\t\t   \t    </div>\r\n\t\t\t\t\t\t\t\t  </li>\r\n\t\t\t\t\t\t\t\t\r\n\t\t\t\t\t   \t       \t\t<li>\r\n\t\t\t\t\t\t\t\t   \t\t<div style=\"float:left;text-align: left;width:500px; \">\r\n\t\t\t\t\t\t\t\t   \t       <a target=\"_blank\" href=\"/eweb/jygl/zpfw.so?modcode=jygl_zpfwzpgg&subsyscode=zpfw&type=view&id=4sTs9gCzGZytcaQF3TQiRB\">\r\n\t\t\t\t\t\t\t\t   \t\t   \t \u4e2d\u56fd\u534e\u7535\u96c6\u56e2\u6709\u9650\u516c\u53f82018\u5e74\u62db\u8058 \r\n\t\t\t\t\t\t\t\t   \t       </a>\r\n\t\t\t\t\t\t\t\t   \t    </div>\r\n\t\t\t\t\t\t\t\t  </li>\r\n\t\t\t\t\t\t\t\t\r\n\t\t\t\t\t   \t       \t\t<li>\r\n\t\t\t\t\t\t\t\t   \t\t<div style=\"float:left;text-align: left;width:500px; \">\r\n\t\t\t\t\t\t\t\t   \t       <a target=\"_blank\" href=\"/eweb/jygl/zpfw.so?modcode=jygl_zpfwzpgg&subsyscode=zpfw&type=view&id=5oQiX3mVfG3Syq6yawwWcv\">\r\n\t\t\t\t\t\t\t\t   \t\t   \t \u56fd\u5bb6\u7535\u529b\u6295\u8d44\u96c6\u56e2\u516c\u53f8\u4eba\u624d\u5b66\u96622018\u5e74\u5e94\u5c4a\u6bd5\u4e1a\u751f\u62db\u8058\u7b80\u7ae0\r\n\t\t\t\t\t\t\t\t   \t       </a>\r\n\t\t\t\t\t\t\t\t   \t    </div>\r\n\t\t\t\t\t\t\t\t  </li>\r\n\t\t\t\t\t\t\t\t\r\n\t\t\t\t\t   \t       \t\t<li>\r\n\t\t\t\t\t\t\t\t   \t\t<div style=\"float:left;text-align: left;width:500px; \">\r\n\t\t\t\t\t\t\t\t   \t       <a target=\"_blank\" href=\"/eweb/jygl/zpfw.so?modcode=jygl_zpfwzpgg&subsyscode=zpfw&type=view&id=Ge4pP7tH34rBKweRFUdANh\">\r\n\t\t\t\t\t\t\t\t   \t\t   \t \u4e0a\u6d77\u98de\u71a0\u8f6f\u4ef6\u6280\u672f\u6709\u9650\u516c\u53f82018\u6821\u56ed\u62db\u8058\uff08\u70ed\u80fd\u4e0e\u52a8\u529b\u5de5\u7a0b\u5e08\uff09\r\n\t\t\t\t\t\t\t\t   \t       </a>\r\n\t\t\t\t\t\t\t\t   \t    </div>\r\n\t\t\t\t\t\t\t\t  </li>\r\n\t\t\t\t\t\t\t\t\r\n\t\t\t\t\t   \t       \t\t<li>\r\n\t\t\t\t\t\t\t\t   \t\t<div style=\"float:left;text-align: left;width:500px; \">\r\n\t\t\t\t\t\t\t\t   \t       <a target=\"_blank\" href=\"/eweb/jygl/zpfw.so?modcode=jygl_zpfwzpgg&subsyscode=zpfw&type=view&id=4e8wk89iAsWkfpc8L3q2ni\">\r\n\t\t\t\t\t\t\t\t   \t\t   \t \u4e0a\u6d77\u901a\u534e\u71c3\u6c14\u8f6e\u673a\u670d\u52a1\u6709\u9650\u516c\u53f8\u62db\u8058\u4fe1\u606f\r\n\t\t\t\t\t\t\t\t   \t       </a>\r\n\t\t\t\t\t\t\t\t   \t    </div>\r\n\t\t\t\t\t\t\t\t  </li>\r\n\t\t\t\t\t\t\t\t\r\n\t\t\t\t\t   \t       \t\t<li>\r\n\t\t\t\t\t\t\t\t   \t\t<div style=\"float:left;text-align: left;width:500px; \">\r\n\t\t\t\t\t\t\t\t   \t       <a target=\"_blank\" href=\"/eweb/jygl/zpfw.so?modcode=jygl_zpfwzpgg&subsyscode=zpfw&type=view&id=94uvkHaThkAC2HZi3BCTZi\">\r\n\t\t\t\t\t\t\t\t   \t\t   \t \u4e2d\u673a\u56fd\u80fd\u6d59\u6c5f\u5de5\u7a0b\u6709\u9650\u516c\u53f8\u6821\u56ed\u62db\u8058\r\n\t\t\t\t\t\t\t\t   \t       </a>\r\n\t\t\t\t\t\t\t\t   \t    </div>\r\n\t\t\t\t\t\t\t\t  </li>\r\n\t\t\t\t\t\t\t\t\r\n\t\t\t                </ul>\r\n                        <div class=\"clear\"></div>\r\n                    </div>\r\n                </div>\r\n                <div class=\"gg_r\">\r\n                \t<h2 class=\"gg_l_tit\"><a href=\"#\">\u5fae\u4fe1\u5173\u6ce8</a></h2>\r\n                \t<li class=\"gg_ewm\">\r\n                        <img width=\"145px\" height=\"135px\" src=\"/eweb/jygl/index/images/shiep_ewm.jpg\" />\r\n                    </li>\r\n                </div>\r\n                <div class=\"clear\"></div>\r\n            </div>\r\n            <div class=\"line_gray\"></div>\r\n            <div class=\"gg_left_bot\">\r\n                <ul class=\"gg_left_bot_left\">\r\n                \t<p class=\"gg_bot_tit\">\u5168\u56fd\u5927\u5b66\u751f\u5c31\u4e1a\u4e00\u7ad9\u5f0f\u670d\u52a1\u7cfb\u7edf\u5165\u53e3</p>\r\n                    <img class=\"gg_xsfw_logo\" src=\"/eweb/jygl/index/images/fuxt_logo.png\" />\r\n                    <div class=\"clear\"></div>\r\n                </ul>\r\n                <ul class=\"gg_left_bot_cen\">\r\n                \t<li><input class=\"stu_btn\" type=\"button\" value=\"\u5b66\u751f\u767b\u5f55\" onclick=\"window.open('http://www.ncss.org.cn/')\"/><a class=\"stu_sc\" href=\"http://file.ncss.org.cn/ncsFile/ncss/guidebook/student_guide.pdf\">\u5b66\u751f\u6307\u5bfc\u624b\u518c</a></li>\r\n                    <li><input class=\"com_btn\" type=\"button\" value=\"\u5355\u4f4d\u767b\u5f55\" onclick=\"window.open('http://www.ncss.org.cn/')\"/><a class=\"stu_sc\" href=\"http://file.ncss.org.cn/ncsFile/ncss/guidebook/rec_guide.pdf\">\u7528\u4eba\u5355\u4f4d\u6307\u5bfc\u624b\u518c</a></li>\r\n                </ul>\r\n                <ul class=\"gg_left_bot_right\">\r\n                \t<p class=\"gg_bot_tit mt30\">\u4e0a\u6d77\u5e02\u5b66\u751f\u4e8b\u52a1\u4e2d\u5fc3\u5b66\u751f\u6fc0\u6d3b\u5165\u53e3</p>\r\n                \t<a href=\"http://www.firstjob.com.cn/eduStu/\"><img class=\"gg_xsfw_logo mt30\" src=\"/eweb/jygl/index/images/jihuo_pic.png\" /></a>\r\n                </ul>\r\n                <div class=\"clear\"></div>\r\n            </div>\r\n        </div>\r\n        <!--\u516c\u544a END-->\r\n       \r\n<!--\u5e95\u90e8-->\r\n    <div class=\"foot\">\r\n        \t<ul class=\"footer_content\">\r\n                <li>&nbsp;&nbsp;&nbsp;&nbsp;\u7248\u6743\u6240\u6709\uff1a\u7814\u7a76\u751f\u5de5\u4f5c\u90e8</li>\r\n                <li>\r\n                \t\u5730\u5740\uff1a\u4e0a\u6d77\u5e02\u6768\u6d66\u533a\u5e73\u51c9\u8def2103\u53f7\u4e00\u6559301\u5ba4 &nbsp;&nbsp;&nbsp;&nbsp;\r\n                \t\u7535\u8bdd\uff1a021-35303496  &nbsp;&nbsp;&nbsp;&nbsp;\r\n                </li>\r\n            </ul>\r\n        </div> \r\n<!--\u5e95\u90e8 END-->\r\n   </body>\r\n</html>",
                "location": "/eweb/login.jsp?reurl=%2F%2Findex.jsp%3Fnull",
                "components": {
                    "jQuery": {
                        "categories": [
                            "JavaScript Libraries"
                        ]
                    }
                },
                "securitytxt_hash": null,
                "server": null,
                "sitemap": null,
                "html_hash": 1621718968
            },
            "os": null,
            "_shodan": {
                "crawler": "a3cc14ebb782071aec2032690d4fd1979446a9ab",
                "id": "677fc4f0-ba0c-46ec-8358-8a4bdf9e058f",
                "module": "http",
                "options": {}
            },
            "opts": {},
            "ip_str": "210.35.88.190"
        }
    ],
    "asn": "AS4538",
    "city": null,
    "isp": "China Education and Research Network Center",
    "longitude": 121.3997,
    "last_update": "2018-10-12T18:11:27.889346",
    "country_code3": "CHN",
    "country_name": "China",
    "ip_str": "210.35.88.190",
    "os": null,
    "ports": [
        80
    ]
}